elements_http_upload/__init__.py
elements_http_upload/__main__.py
elements_http_upload/_version.py
elements_http_upload/models.py
elements_http_upload/py.typed
elements_http_upload/upload.py
elements_http_upload-0.1.0.dist-info/licenses/LICENSES/Apache-2.0.txt
elements_http_upload-0.1.0.dist-info/licenses/LICENSES/CC-BY-4.0.txt
elements_http_upload-0.1.0.dist-info/licenses/LICENSES/CC0-1.0.txt
elements_http_upload-0.1.0.dist-info/METADATA
elements_http_upload-0.1.0.dist-info/WHEEL
elements_http_upload-0.1.0.dist-info/entry_points.txt
elements_http_upload-0.1.0.dist-info/top_level.txt
elements_http_upload-0.1.0.dist-info/RECORD
