Metadata-Version: 2.4
Name: elements-http-upload
Version: 0.1.0
Summary: A small convenience command-line utility to upload files via HTTP to an elements instance
Author-email: "Philipp S. Sommer" <philipp.sommer@hereon.de>
Maintainer-email: "Philipp S. Sommer" <philipp.sommer@hereon.de>
License: Apache-2.0
Project-URL: Homepage, https://codebase.helmholtz.cloud/hcdc/elements/elements-http-upload
Project-URL: Documentation, https://elements-http-upload.readthedocs.io/en/latest/
Project-URL: Source, https://codebase.helmholtz.cloud/hcdc/elements/elements-http-upload
Project-URL: Tracker, https://codebase.helmholtz.cloud/hcdc/elements/elements-http-upload/issues/
Keywords: datahub,elements,mams,python,http,file transfer
Classifier: Intended Audience :: Developers
Classifier: License :: OSI Approved :: European Union Public Licence 1.2 (EUPL 1.2)
Classifier: Operating System :: OS Independent
Classifier: Programming Language :: Python
Classifier: Programming Language :: Python :: 3
Classifier: Programming Language :: Python :: 3 :: Only
Classifier: Programming Language :: Python :: 3.9
Classifier: Programming Language :: Python :: 3.10
Classifier: Typing :: Typed
Requires-Python: >=3.9
License-File: LICENSES/Apache-2.0.txt
License-File: LICENSES/CC-BY-4.0.txt
License-File: LICENSES/CC0-1.0.txt
Requires-Dist: pydantic>=2.0
Requires-Dist: pydantic-settings
Requires-Dist: requests
Requires-Dist: progressbar2
Provides-Extra: testsite
Requires-Dist: tox; extra == "testsite"
Requires-Dist: isort==5.12.0; extra == "testsite"
Requires-Dist: black==23.1.0; extra == "testsite"
Requires-Dist: blackdoc==0.3.8; extra == "testsite"
Requires-Dist: flake8==6.0.0; extra == "testsite"
Requires-Dist: pre-commit; extra == "testsite"
Requires-Dist: mypy; extra == "testsite"
Requires-Dist: pytest-cov; extra == "testsite"
Requires-Dist: reuse; extra == "testsite"
Requires-Dist: cffconvert; extra == "testsite"
Requires-Dist: types-requests; extra == "testsite"
Provides-Extra: docs
Requires-Dist: sphinx-argparse; extra == "docs"
Requires-Dist: autodocsumm; extra == "docs"
Requires-Dist: sphinx-rtd-theme; extra == "docs"
Requires-Dist: hereon-netcdf-sphinxext; extra == "docs"
Requires-Dist: sphinx-design; extra == "docs"
Requires-Dist: myst_parser; extra == "docs"
Provides-Extra: dev
Requires-Dist: elements-http-upload[testsite]; extra == "dev"
Requires-Dist: elements-http-upload[docs]; extra == "dev"
Requires-Dist: reuse-shortcuts>=1.0.1; extra == "dev"
Requires-Dist: types-PyYAML; extra == "dev"
Dynamic: license-file
